OSGRMATT/__init__.py
OSGRMATT/api.py
OSGRMATT/browser.py
OSGRMATT/cli.py
OSGRMATT/conftest.py
OSGRMATT/db.py
OSGRMATT/decorators.py
OSGRMATT/mailer.py
OSGRMATT/notifier.py
OSGRMATT/screen_recorder.py
OSGRMATT/utils.py
OSGRMATT-0.2.5.dist-info/METADATA
OSGRMATT-0.2.5.dist-info/WHEEL
OSGRMATT-0.2.5.dist-info/entry_points.txt
OSGRMATT-0.2.5.dist-info/top_level.txt
OSGRMATT-0.2.5.dist-info/RECORD
